mux.v
module mux (
    input  wire         sel,    
    input  wire [31:0]  input1,    
    input  wire [31:0]  input2,    
    output wire [31:0]  out
);

    // Combinational logic
    assign out = sel ? input1 : input2;

endmodule

pipelined/Data_memory.v
module data_memory(
    input  wire        clock,        
    input  wire        write_enable,         
    input  wire [31:0] address,       
    input  wire [31:0] write_data,         
    output reg  [31:0] read_data          
);

    // Memory size: 32 KB
    parameter MEM_SIZE = 8192;     
    reg [31:0] memory [0:MEM_SIZE-1];

    // Sequential logic read
    always @(posedge clock) begin
        if (address[31:2] < MEM_SIZE) begin
            read_data <= memory[address[31:2]];
        end else begin
            read_data <= 32'h00000000;  // Out of bounds
        end
    end

    // Sequential logic write
    always @(posedge clock) begin
        if (write_enable && address[31:2] < MEM_SIZE) begin
            memory[address[31:2]] <= write_data;
        end else begin
            read_data <= 32'h00000000;  // Out of bounds
        end
    end

endmodule

single_cycle/ALU.v
module ALU(
    input  wire [31:0] RD1,
    input  wire [31:0] RD2,
    input  wire [3:0]  alu_control,
    output reg  [31:0] alu_result
);

    reg [31:0] addition_result;
    reg [31:0] shifted_operand_b;

    // Combinational logic
    always @(*) begin
        if (alu_control[0] && (alu_control[3:1] == 3'b000 || 
                               alu_control[3:1] == 3'b010 || 
                               alu_control[3:1] == 3'b011)) begin
            shifted_operand_b = ~RD2 + 32'd1;
        end else begin
            shifted_operand_b = RD2;
        end

        addition_result = RD1 + shifted_operand_b;

        case (alu_control)
            4'b0000: begin
                alu_result = addition_result;
            end
            
            4'b0001: begin
                alu_result = addition_result;
            end

            4'b0010: begin
                alu_result = RD1 << RD2[4:0];
            end

            4'b1010: begin
                alu_result = RD1 >> RD2[4:0];
            end

            4'b1011: begin
                alu_result = $signed(RD1) >>> RD2[4:0];
            end

            4'b0100: begin
                alu_result = {31'b0, addition_result[31]};
            end

            4'b0110: begin
                alu_result = {31'b0, (RD1 < RD2)};
            end

            4'b1000: begin
                alu_result = RD1 ^ RD2;
            end

            4'b1100: begin
                alu_result = RD1 | RD2;
            end

            4'b1110: begin
                alu_result = RD1 & RD2;
            end

            default: begin
                alu_result = addition_result;
            end
        endcase
    end

endmodule

sign_extender.v
module sign_extender(
    input  wire [31:0] instruction,
    input  wire [2:0]  sel_ext,          
    output reg  [31:0] imm_extended           
);

    reg [11:0] immediate_12bit;
    reg [12:0] immediate_13bit;
    reg [20:0] immediate_21bit;
    reg [19:0] immediate_20bit;
    reg        sign_bit;
    
    // Combinational logic
    always @(*) begin
        case (sel_ext)

            // I-type: imm[11:0] from I-type
            3'b000: begin
                immediate_12bit = instruction[31:20];
                sign_bit = immediate_12bit[11];
                
                if (sign_bit) begin
                    imm_extended = {20'hFFFFF, immediate_12bit};
                end else begin
                    imm_extended = {20'h00000, immediate_12bit};
                end
            end
            
            // S-type: imm[11:0] from S-type
            3'b001: begin
                immediate_12bit = {instruction[31:25], instruction[11:7]};
                sign_bit = immediate_12bit[11];
                
                if (sign_bit) begin
                    imm_extended = {20'hFFFFF, immediate_12bit};
                end else begin
                    imm_extended = {20'h00000, immediate_12bit};
                end
            end

            // B-type: imm[12:0] from B-type
            3'b010: begin
                immediate_13bit = {instruction[31], instruction[7], instruction[30:25], 
                                   instruction[11:8], 1'b0};
                sign_bit = immediate_13bit[12];
                
                if (sign_bit) begin
                    imm_extended = {19'h7FFFF, immediate_13bit};
                end else begin
                    imm_extended = {19'h00000, immediate_13bit};
                end
            end
            
            // U-type: imm[31:12] from U-type
            3'b011: begin
                immediate_20bit = instruction[31:12];
                imm_extended = {immediate_20bit, 12'b0};
            end

            // J-type: imm[20:0] from J-type
            3'b100: begin
                immediate_21bit = {instruction[31], instruction[19:12], instruction[20],
                                   instruction[30:21], 1'b0};
                sign_bit = immediate_21bit[20];
                
                if (sign_bit) begin
                    imm_extended = {11'h7FF, immediate_21bit};
                end else begin
                    imm_extended = {11'h000, immediate_21bit};
                end
            end

            // Default case: wrong input 
            default: begin
                imm_extended = 32'h00000000;
            end
        endcase
    end

endmodule

register_file.v
module register_file(
    input  wire        clock,
    input  wire        write_enable,
    input  wire [4:0]  read_address_1,
    input  wire [4:0]  read_address_2,
    input  wire [4:0]  write_address,
    input  wire [31:0] write_data,
    
    output reg  [31:0] read_data_1,
    output reg  [31:0] read_data_2
);
    reg [31:0] registers [0:31];

    // Combinational read RD1
    always @(*) begin
        if (read_address_1 == 5'b00000) begin
            read_data_1 = 32'h00000000;
        end else begin
            read_data_1 = registers[read_address_1];
        end
    end

    // Combinational read RD2
    always @(*) begin
        if (read_address_2 == 5'b00000) begin
            read_data_2 = 32'h00000000;
        end else begin
            read_data_2 = registers[read_address_2];
        end
    end

    // Sequential write
    always @(posedge clock) begin
        if (write_enable && write_address != 5'b00000) begin
            registers[write_address] <= write_data;
        end
    end

endmodule

controller.v
module controller(
    input wire [31:0] instruction,

    output reg         rf_we,
    output reg  [2:0]  sel_ext,
    output reg         sel_alu_src_b,
    output reg         dmem_we,
    output reg  [1:0]  sel_result,
    output reg         sel_pc_src,
    output reg  [3:0]  alu_control
);

    wire [6:0] opcode;
    wire [2:0] funct3;
    wire [6:0] funct7;
    
    assign opcode = instruction[6:0];
    assign funct3 = instruction[14:12];
    assign funct7 = instruction[31:25];
    
    reg [1:0] alu_op;

    // First Level Decoding
    always @(*) begin
        case (opcode)
            // I-type lw
            7'b0000011: begin
                rf_we = 1'b1;
                sel_ext = 3'b000;
                sel_alu_src_b = 1'b1;
                dmem_we = 1'b0;
                sel_result = 2'b01;
                sel_pc_src = 1'b0;
                alu_op = 2'b00;
            end
            
            // S-type sw
            7'b0100011: begin
                rf_we = 1'b0;
                sel_ext = 3'b001;
                sel_alu_src_b = 1'b1;
                dmem_we = 1'b1;
                sel_result = 2'b00;
                sel_pc_src = 1'b0;
                alu_op = 2'b00;
            end
            
            // R-type
            7'b0110011: begin
                rf_we = 1'b1;
                sel_ext = 3'b000;
                sel_alu_src_b = 1'b0;
                dmem_we = 1'b0;
                sel_result = 2'b00;
                sel_pc_src = 1'b0;
                alu_op = 2'b01;
            end
            
            // I-type
            7'b0010011: begin
                rf_we = 1'b1;
                sel_ext = 3'b000;
                sel_alu_src_b = 1'b1;
                dmem_we = 1'b0;
                sel_result = 2'b00;
                sel_pc_src = 1'b0;
                alu_op = 2'b10;
            end
            
            // J-type jal
            7'b1101111: begin
                rf_we = 1'b1;
                sel_ext = 3'b100;
                sel_alu_src_b = 1'b0;
                dmem_we = 1'b0;
                sel_result = 2'b10;
                sel_pc_src = 1'b1;
                alu_op = 2'b00;
            end
            
            // U-type lui
            7'b0110111: begin
                rf_we = 1'b1;
                sel_ext = 3'b011;
                sel_alu_src_b = 1'b0;
                dmem_we = 1'b0;
                sel_result = 2'b11;
                sel_pc_src = 1'b0;
                alu_op = 2'b00;
            end
            
            // Default case error 
            default: begin
                rf_we = 1'b0;
                sel_ext = 3'b000;
                sel_alu_src_b = 1'b0;
                dmem_we = 1'b0;
                sel_result = 2'b00;
                sel_pc_src = 1'b0;
                alu_op = 2'b00;
            end
        endcase
    end

    // Second Level Decoding
    always @(*) begin
        case (alu_op)
            2'b00: begin
                alu_control = 4'b0000;
            end
            // R-type and I-type
            2'b01, 2'b10: begin
                alu_control = {funct3, funct7[5]};
            end
            // Default case
            default: begin
                alu_control = 4'b0000;
            end
        endcase
    end

endmodule

instructoin_memory.v
module instructoin_memory(
    input  wire [31:0] pc,              
    output reg  [31:0] instruction      
);

    // Memory size: 32 KB
    parameter MEM_SIZE = 8192;     
    reg [31:0] memory [0:MEM_SIZE-1];

    initial begin
        $readmemh("program.hex", memory);
    end

    // Combinational logic
    always @(*) begin
        if (pc[31:2] < MEM_SIZE) begin  // Check in case address out of bounds
            instruction = memory[pc[31:2]];
        end else begin
            instruction = 32'h00000013; // NOP
        end
    end

endmodule

pipelined/add_pc_imm.v
// PC + Immediate Adder Module (for branch/jump target)
module add_pc_imm(
    input  wire [31:0] pc,
    input  wire [31:0] imm_extended,
    output wire [31:0] pc_plus_imm
);

    assign pc_plus_imm = pc + imm_extended;

endmodule

single_cycle/add.v
module add(
    input  wire [31:0] pc,
    output wire [31:0] next_pc
);

    assign next_pc = pc + 4;

endmodule

single_cycle/Program_counter.v
module program_counter(
    input  wire        clk, 
    input  wire [31:0] next_pc,
    output reg  [31:0] pc
);

    initial begin
        pc = 32'h00000000;
    end

    always @(posedge clk) begin
        pc <= next_pc;
    end

endmodule

main.v
module main(
    input  wire clock
);

    // Internal wires
    wire [31:0] pc;
    wire [31:0] next_pc;
    wire [31:0] pc_plus_4;
    wire [31:0] pc_plus_imm;
    wire [31:0] instruction;
    wire [31:0] rd1;
    wire [31:0] rd2;
    wire [31:0] imm_extended;
    wire [31:0] alu_operand_b;
    wire [31:0] alu_result;
    wire [31:0] dmem_read_data;
    wire [31:0] rf_write_data;
    wire [31:0] mux_result_intermediate;
    wire [31:0] mux_result_pc_imm;
    
    // Controller
    wire        rf_we;
    wire [2:0]  sel_ext;
    wire        sel_alu_src_b;
    wire [3:0]  alu_control;
    wire        dmem_we;
    wire [1:0]  sel_result;
    wire        sel_pc_src;
    
    // Instruction field extraction
    wire [4:0]  rs1 = instruction[19:15];
    wire [4:0]  rs2 = instruction[24:20];
    wire [4:0]  rd  = instruction[11:7];

    // Program Counter
    program_counter pc_module(
        .clk(clock),
        .next_pc(next_pc),
        .pc(pc)
    );

    // Adder for PC + 4
    add pc_adder(
        .pc(pc),
        .next_pc(pc_plus_4)
    );
    
    // Adder for PC + immediate JAL
    add_pc_imm add_pc_imm(
        .pc(pc),
        .imm_extended(imm_extended),
        .pc_plus_imm(pc_plus_imm)
    );
    
    // MUX for PC source: PC+4 (normal) or PC+imm (jump)
    mux mux_pc_src(
        .sel(sel_pc_src),
        .input1(pc_plus_imm),
        .input2(pc_plus_4),
        .out(next_pc)
    );

    // Instruction Memory
    instructoin_memory inst_mem(
        .pc(pc),
        .instruction(instruction)
    );

    // Controller
    controller ctrl(
        .instruction(instruction),
        .rf_we(rf_we),
        .sel_ext(sel_ext),
        .sel_alu_src_b(sel_alu_src_b),
        .dmem_we(dmem_we),
        .sel_result(sel_result),
        .sel_pc_src(sel_pc_src),
        .alu_control(alu_control)
    );

    // Register File
    register_file rf(
        .clock(clock),
        .write_enable(rf_we),
        .read_address_1(rs1),
        .read_address_2(rs2),
        .write_address(rd),
        .write_data(rf_write_data),
        .read_data_1(rd1),
        .read_data_2(rd2)
    );

    // Sign Extender
    sign_extender sign_ext(
        .instruction(instruction),
        .sel_ext(sel_ext),
        .imm_extended(imm_extended)
    );

    // MUX for ALU Left
    mux mux_alu_src_b(
        .sel(sel_alu_src_b),
        .input1(rd2),
        .input2(imm_extended),
        .out(alu_operand_b)
    );

    // ALU
    ALU alu(
        .RD1(rd1),
        .RD2(alu_operand_b),
        .alu_control(alu_control),
        .alu_result(alu_result)
    );

    // Data Memory
    data_memory dmem(
        .clock(clock),
        .write_enable(dmem_we),
        .address(alu_result),
        .write_data(rd2),
        .read_data(dmem_read_data)
    );

    // MUX for Result alu to mem
    mux mux_result_alu_mem(
        .sel(sel_result[0]),
        .input1(alu_result),
        .input2(dmem_read_data),
        .out(mux_result_intermediate)
    );
    
    // MUX for Result pc imm
    mux mux_result_pc_imm_mux(
        .sel(sel_result[0]),
        .input1(pc_plus_4),
        .input2(imm_extended),
        .out(mux_result_pc_imm)
    );
    
    // MUX for Result: Final selection
    mux mux_result_final(
        .sel(sel_result[1]),
        .input1(mux_result_intermediate),
        .input2(mux_result_pc_imm),
        .out(rf_write_data)
    );

endmodule

testbench.v
module testbench;

    reg clock;
    
    main dut(
        .clock(clock)
    );
    
    initial begin
        clock = 0;
        forever #10 clock = ~clock;
    end
    
    initial begin
        $dumpfile("riscv_processor.vcd");
        $dumpvars(0, testbench);
    end

    initial begin
        #20000;
        $display("Simulation completed time: %0t", $time);
        $display("Final PC: 0x%h", dut.pc);
        
        $finish;
    end
    
    //Debugging
    initial begin
        $monitor("Time: %0t | PC: 0x%h | next_pc: 0x%h | pc_plus_4: 0x%h | sel_pc_src: %b | Instruction: 0x%h | ALU Result: 0x%h", 
                 $time, dut.pc, dut.next_pc, dut.pc_plus_4, dut.sel_pc_src, dut.instruction, dut.alu_result);
    end

endmodule

riscv_processor.vcd
$date
	Thu Dec  4 17:00:57 2025
$end
$version
	Icarus Verilog
$end
$timescale
	1s
$end
$scope module testbench $end
$var reg 1 ! clock $end
$scope module dut $end
$var wire 1 ! clock $end
$var wire 2 " sel_result [1:0] $end
$var wire 1 # sel_pc_src $end
$var wire 3 $ sel_ext [2:0] $end
$var wire 1 % sel_alu_src_b $end
$var wire 5 & rs2 [4:0] $end
$var wire 5 ' rs1 [4:0] $end
$var wire 32 ( rf_write_data [31:0] $end
$var wire 1 ) rf_we $end
$var wire 32 * rd2 [31:0] $end
$var wire 32 + rd1 [31:0] $end
$var wire 5 , rd [4:0] $end
$var wire 32 - pc_plus_imm [31:0] $end
$var wire 32 . pc_plus_4 [31:0] $end
$var wire 32 / pc [31:0] $end
$var wire 32 0 next_pc [31:0] $end
$var wire 32 1 mux_result_pc_imm [31:0] $end
$var wire 32 2 mux_result_intermediate [31:0] $end
$var wire 32 3 instruction [31:0] $end
$var wire 32 4 imm_extended [31:0] $end
$var wire 1 5 dmem_we $end
$var wire 32 6 dmem_read_data [31:0] $end
$var wire 32 7 alu_result [31:0] $end
$var wire 32 8 alu_operand_b [31:0] $end
$var wire 4 9 alu_control [3:0] $end
$scope module add_pc_imm $end
$var wire 32 : pc_plus_imm [31:0] $end
$var wire 32 ; pc [31:0] $end
$var wire 32 < imm_extended [31:0] $end
$upscope $end
$scope module alu $end
$var wire 4 = alu_control [3:0] $end
$var wire 32 > RD2 [31:0] $end
$var wire 32 ? RD1 [31:0] $end
$var reg 32 @ addition_result [31:0] $end
$var reg 32 A alu_result [31:0] $end
$var reg 32 B shifted_operand_b [31:0] $end
$upscope $end
$scope module ctrl $end
$var wire 7 C opcode [6:0] $end
$var wire 32 D instruction [31:0] $end
$var wire 7 E funct7 [6:0] $end
$var wire 3 F funct3 [2:0] $end
$var reg 4 G alu_control [3:0] $end
$var reg 2 H alu_op [1:0] $end
$var reg 1 5 dmem_we $end
$var reg 1 ) rf_we $end
$var reg 1 % sel_alu_src_b $end
$var reg 3 I sel_ext [2:0] $end
$var reg 1 # sel_pc_src $end
$var reg 2 J sel_result [1:0] $end
$upscope $end
$scope module dmem $end
$var wire 32 K address [31:0] $end
$var wire 1 ! clock $end
$var wire 1 5 write_enable $end
$var wire 32 L write_data [31:0] $end
$var reg 32 M read_data [31:0] $end
$upscope $end
$scope module inst_mem $end
$var wire 32 N pc [31:0] $end
$var reg 32 O instruction [31:0] $end
$upscope $end
$scope module mux_alu_src_b $end
$var wire 1 % sel $end
$var wire 32 P out [31:0] $end
$var wire 32 Q input2 [31:0] $end
$var wire 32 R input1 [31:0] $end
$upscope $end
$scope module mux_pc_src $end
$var wire 32 S input1 [31:0] $end
$var wire 1 # sel $end
$var wire 32 T out [31:0] $end
$var wire 32 U input2 [31:0] $end
$upscope $end
$scope module mux_result_alu_mem $end
$var wire 32 V input1 [31:0] $end
$var wire 32 W input2 [31:0] $end
$var wire 1 X sel $end
$var wire 32 Y out [31:0] $end
$upscope $end
$scope module mux_result_final $end
$var wire 32 Z input1 [31:0] $end
$var wire 1 [ sel $end
$var wire 32 \ out [31:0] $end
$var wire 32 ] input2 [31:0] $end
$upscope $end
$scope module mux_result_pc_imm_mux $end
$var wire 1 ^ sel $end
$var wire 32 _ out [31:0] $end
$var wire 32 ` input2 [31:0] $end
$var wire 32 a input1 [31:0] $end
$upscope $end
$scope module pc_adder $end
$var wire 32 b pc [31:0] $end
$var wire 32 c next_pc [31:0] $end
$upscope $end
$scope module pc_module $end
$var wire 1 ! clk $end
$var wire 32 d next_pc [31:0] $end
$var reg 32 e pc [31:0] $end
$upscope $end
$scope module rf $end
$var wire 1 ! clock $end
$var wire 5 f read_address_1 [4:0] $end
$var wire 5 g read_address_2 [4:0] $end
$var wire 5 h write_address [4:0] $end
$var wire 32 i write_data [31:0] $end
$var wire 1 ) write_enable $end
$var reg 32 j read_data_1 [31:0] $end
$var reg 32 k read_data_2 [31:0] $end
$upscope $end
$scope module sign_ext $end
$var wire 32 l instruction [31:0] $end
$var wire 3 m sel_ext [2:0] $end
$var reg 32 n imm_extended [31:0] $end
$var reg 12 o immediate_12bit [11:0] $end
$var reg 13 p immediate_13bit [12:0] $end
$var reg 20 q immediate_20bit [19:0] $end
$var reg 21 r immediate_21bit [20:0] $end
$var reg 1 s sign_bit $end
$upscope $end
$upscope $end
$upscope $end
$enddefinitions $end
#0
$dumpvars
0s
bx r
bx q
bx p
b101 o
b101 n
b0 m
b10100000000000010010011 l
bx k
b0 j
b101 i
b1 h
b101 g
b0 f
b0 e
b100 d
b100 c
b0 b
b100 a
b101 `
b101 _
0^
b101 ]
b101 \
0[
bx Z
bx Y
0X
bx W
bx V
b100 U
b100 T
b101 S
bx R
b101 Q
bx P
b10100000000000010010011 O
b0 N
bx M
bx L
bx K
b0 J
b0 I
b10 H
b0 G
b0 F
b0 E
b10100000000000010010011 D
b10011 C
bx B
bx A
bx @
b0 ?
bx >
b0 =
b101 <
b0 ;
b101 :
b0 9
bx 8
bx 7
bx 6
05
b101 4
b10100000000000010010011 3
bx 2
b101 1
b100 0
b0 /
b100 .
b101 -
b1 ,
b0 +
bx *
1)
b101 (
b0 '
b101 &
1%
b0 $
0#
b0 "
0!
$end
#10
b1010 (
b1010 \
b1010 i
b1010 1
b1010 ]
b1010 _
b10 ,
b10 h
b1010 &
b1010 g
b1010 4
b1010 <
b1010 Q
b1010 `
b1010 n
b1010 o
b1000 0
b1000 T
b1000 d
b101000000000000100010011 3
b101000000000000100010011 D
b101000000000000100010011 O
b101000000000000100010011 l
b0 2
b0 Y
b0 Z
b1000 .
b1000 U
b1000 a
b1000 c
b1110 -
b1110 :
b1110 S
b100 /
b100 ;
b100 N
b100 b
b100 e
b0 6
b0 M
b0 W
1!
#20
0!
#30
b1010 @
b101 B
b101 8
b101 >
b101 P
b0 7
b0 A
b0 K
b0 V
b1 (
b1 \
b1 i
b100 9
b100 =
b100 G
b101 *
b101 L
b101 R
b101 k
b101 +
b101 ?
b101 j
b1 1
b1 ]
b1 _
b10 F
b11 ,
b11 h
b1 &
b1 g
b1 '
b1 f
b1 4
b1 <
b1 Q
b1 `
b1 n
b1 o
b1100 0
b1100 T
b1100 d
b100001010000110010011 3
b100001010000110010011 D
b100001010000110010011 O
b100001010000110010011 l
b1100 .
b1100 U
b1100 a
b1100 c
b1001 -
b1001 :
b1001 S
b1000 /
b1000 ;
b1000 N
b1000 b
b1000 e
1!
#40
0!
#50
b110 9
b110 =
b110 G
b11 F
b100 ,
b100 h
b10000 0
b10000 T
b10000 d
b100001011001000010011 3
b100001011001000010011 D
b100001011001000010011 O
b100001011001000010011 l
bx 2
bx Y
bx Z
b10000 .
b10000 U
b10000 a
b10000 c
b1101 -
b1101 :
b1101 S
b1100 /
b1100 ;
b1100 N
b1100 b
b1100 e
bx 6
bx M
bx W
1!
#60
0!
#70
b1000 9
b1000 =
b1000 G
b100 F
b101 ,
b101 h
b0 2
b0 Y
b0 Z
b10100 0
b10100 T
b10100 d
b100001100001010010011 3
b100001100001010010011 D
b100001100001010010011 O
b100001100001010010011 l
b0 6
b0 M
b0 W
b10100 .
b10100 U
b10100 a
b10100 c
b10001 -
b10001 :
b10001 S
b10000 /
b10000 ;
b10000 N
b10000 b
b10000 e
1!
#80
0!
#90
b101 7
b101 A
b101 K
b101 V
b1100 9
b1100 =
b1100 G
b110 F
b110 ,
b110 h
b11000 0
b11000 T
b11000 d
b100001110001100010011 3
b100001110001100010011 D
b100001110001100010011 O
b100001110001100010011 l
bx 2
bx Y
bx Z
b11000 .
b11000 U
b11000 a
b11000 c
b10101 -
b10101 :
b10101 S
b10100 /
b10100 ;
b10100 N
b10100 b
b10100 e
bx 6
bx M
bx W
1!
#100
0!
#110
b1110 9
b1110 =
b1110 G
b111 F
b111 ,
b111 h
b0 2
b0 Y
b0 Z
b11100 0
b11100 T
b11100 d
b100001111001110010011 3
b100001111001110010011 D
b100001111001110010011 O
b100001111001110010011 l
b0 6
b0 M
b0 W
b11100 .
b11100 U
b11100 a
b11100 c
b11001 -
b11001 :
b11001 S
b11000 /
b11000 ;
b11000 N
b11000 b
b11000 e
1!
#120
0!
#130
b10100000 7
b10100000 A
b10100000 K
b10100000 V
b10 9
b10 =
b10 G
b1 F
b10 ,
b10 h
b100000 0
b100000 T
b100000 d
b100001001000100010011 3
b100001001000100010011 D
b100001001000100010011 O
b100001001000100010011 l
bx 2
bx Y
bx Z
b100000 .
b100000 U
b100000 a
b100000 c
b11101 -
b11101 :
b11101 S
b11100 /
b11100 ;
b11100 N
b11100 b
b11100 e
bx 6
bx M
bx W
1!
#140
0!
#150
b0 7
b0 A
b0 K
b0 V
b1010 9
b1010 =
b1010 G
b101 F
b11 ,
b11 h
b0 2
b0 Y
b0 Z
b100100 0
b100100 T
b100100 d
b100001101000110010011 3
b100001101000110010011 D
b100001101000110010011 O
b100001101000110010011 l
b0 6
b0 M
b0 W
b100100 .
b100100 U
b100100 a
b100100 c
b100001 -
b100001 :
b100001 S
b100000 /
b100000 ;
b100000 N
b100000 b
b100000 e
1!
#160
0!
#170
b10000000001 (
b10000000001 \
b10000000001 i
b1011 9
b1011 =
b1011 G
b10000000001 1
b10000000001 ]
b10000000001 _
b100000 E
b100 ,
b100 h
b10000000001 4
b10000000001 <
b10000000001 Q
b10000000001 `
b10000000001 n
b10000000001 o
b101000 0
b101000 T
b101000 d
b1000000000100001101001000010011 3
b1000000000100001101001000010011 D
b1000000000100001101001000010011 O
b1000000000100001101001000010011 l
bx 2
bx Y
bx Z
b101000 .
b101000 U
b101000 a
b101000 c
b10000100101 -
b10000100101 :
b10000100101 S
b100100 /
b100100 ;
b100100 N
b100100 b
b100100 e
bx 6
bx M
bx W
1!
#180
0!
#190
b111 7
b111 A
b111 K
b111 V
b111 @
b10 B
b10 8
b10 >
b10 P
b10 (
b10 \
b10 i
b0 9
b0 =
b0 G
b1 H
0%
b1 *
b1 L
b1 R
b1 k
b10 1
b10 ]
b10 _
b0 E
b0 F
b110011 C
b11 ,
b11 h
b10 &
b10 g
b10 4
b10 <
b10 Q
b10 `
b10 n
b10 o
b0 2
b0 Y
b0 Z
b101100 0
b101100 T
b101100 d
b1000001000000110110011 3
b1000001000000110110011 D
b1000001000000110110011 O
b1000001000000110110011 l
b0 6
b0 M
b0 W
b101100 .
b101100 U
b101100 a
b101100 c
b101010 -
b101010 :
b101010 S
b101000 /
b101000 ;
b101000 N
b101000 b
b101000 e
1!
#200
0!
#210
b10000000010 (
b10000000010 \
b10000000010 i
b11111111111111111111110000000011 7
b11111111111111111111110000000011 A
b11111111111111111111110000000011 K
b11111111111111111111110000000011 V
b11111111111111111111110000000011 @
b11111111111111111111101111111110 B
b1 9
b1 =
b1 G
b10000000010 1
b10000000010 ]
b10000000010 _
b10000000010 8
b10000000010 >
b10000000010 P
b100000 E
b10000000010 4
b10000000010 <
b10000000010 Q
b10000000010 `
b10000000010 n
b10000000010 o
b110000 0
b110000 T
b110000 d
b1000000001000001000000110110011 3
b1000000001000001000000110110011 D
b1000000001000001000000110110011 O
b1000000001000001000000110110011 l
bx 2
bx Y
bx Z
b110000 .
b110000 U
b110000 a
b110000 c
b10000101110 -
b10000101110 :
b10000101110 S
b101100 /
b101100 ;
b101100 N
b101100 b
b101100 e
bx 6
bx M
bx W
1!
#220
0!
#230
b10 (
b10 \
b10 i
b10100 7
b10100 A
b10100 K
b10100 V
b111 @
b10 B
b10 9
b10 =
b10 G
b10 1
b10 ]
b10 _
b10 8
b10 >
b10 P
b0 E
b1 F
b10 4
b10 <
b10 Q
b10 `
b10 n
b10 o
b0 2
b0 Y
b0 Z
b110100 0
b110100 T
b110100 d
b1000001001000110110011 3
b1000001001000110110011 D
b1000001001000110110011 O
b1000001001000110110011 l
b0 6
b0 M
b0 W
b110100 .
b110100 U
b110100 a
b110100 c
b110010 -
b110010 :
b110010 S
b110000 /
b110000 ;
b110000 N
b110000 b
b110000 e
1!
#240
0!
#250
b0 7
b0 A
b0 K
b0 V
b100 9
b100 =
b100 G
b10 F
b111000 0
b111000 T
b111000 d
b1000001010000110110011 3
b1000001010000110110011 D
b1000001010000110110011 O
b1000001010000110110011 l
bx 2
bx Y
bx Z
b111000 .
b111000 U
b111000 a
b111000 c
b110110 -
b110110 :
b110110 S
b110100 /
b110100 ;
b110100 N
b110100 b
b110100 e
bx 6
bx M
bx W
1!
#260
0!
#270
b110 9
b110 =
b110 G
b11 F
b0 2
b0 Y
b0 Z
b111100 0
b111100 T
b111100 d
b1000001011000110110011 3
b1000001011000110110011 D
b1000001011000110110011 O
b1000001011000110110011 l
b0 6
b0 M
b0 W
b111100 .
b111100 U
b111100 a
b111100 c
b111010 -
b111010 :
b111010 S
b111000 /
b111000 ;
b111000 N
b111000 b
b111000 e
1!
#280
0!
#290
b111 7
b111 A
b111 K
b111 V
b1000 9
b1000 =
b1000 G
b100 F
b1000000 0
b1000000 T
b1000000 d
b1000001100000110110011 3
b1000001100000110110011 D
b1000001100000110110011 O
b1000001100000110110011 l
bx 2
bx Y
bx Z
b1000000 .
b1000000 U
b1000000 a
b1000000 c
b111110 -
b111110 :
b111110 S
b111100 /
b111100 ;
b111100 N
b111100 b
b111100 e
bx 6
bx M
bx W
1!
#300
0!
#310
b1 7
b1 A
b1 K
b1 V
b1010 9
b1010 =
b1010 G
b101 F
b0 2
b0 Y
b0 Z
b1000100 0
b1000100 T
b1000100 d
b1000001101000110110011 3
b1000001101000110110011 D
b1000001101000110110011 O
b1000001101000110110011 l
b0 6
b0 M
b0 W
b1000100 .
b1000100 U
b1000100 a
b1000100 c
b1000010 -
b1000010 :
b1000010 S
b1000000 /
b1000000 ;
b1000000 N
b1000000 b
b1000000 e
1!
#320
0!
#330
b10000000010 (
b10000000010 \
b10000000010 i
b10000000111 @
b10000000010 B
b1011 9
b1011 =
b1011 G
b10000000010 1
b10000000010 ]
b10000000010 _
b10000000010 8
b10000000010 >
b10000000010 P
b100000 E
b10000000010 4
b10000000010 <
b10000000010 Q
b10000000010 `
b10000000010 n
b10000000010 o
b1001000 0
b1001000 T
b1001000 d
b1000000001000001101000110110011 3
b1000000001000001101000110110011 D
b1000000001000001101000110110011 O
b1000000001000001101000110110011 l
bx 2
bx Y
bx Z
b1001000 .
b1001000 U
b1001000 a
b1001000 c
b10001000110 -
b10001000110 :
b10001000110 S
b1000100 /
b1000100 ;
b1000100 N
b1000100 b
b1000100 e
bx 6
bx M
bx W
1!
#340
0!
#350
b10 (
b10 \
b10 i
b111 7
b111 A
b111 K
b111 V
b111 @
b10 B
b1100 9
b1100 =
b1100 G
b10 1
b10 ]
b10 _
b10 8
b10 >
b10 P
b0 E
b110 F
b10 4
b10 <
b10 Q
b10 `
b10 n
b10 o
b0 2
b0 Y
b0 Z
b1001100 0
b1001100 T
b1001100 d
b1000001110000110110011 3
b1000001110000110110011 D
b1000001110000110110011 O
b1000001110000110110011 l
b0 6
b0 M
b0 W
b1001100 .
b1001100 U
b1001100 a
b1001100 c
b1001010 -
b1001010 :
b1001010 S
b1001000 /
b1001000 ;
b1001000 N
b1001000 b
b1001000 e
1!
#360
0!
#370
b0 7
b0 A
b0 K
b0 V
b1110 9
b1110 =
b1110 G
b111 F
b1010000 0
b1010000 T
b1010000 d
b1000001111000110110011 3
b1000001111000110110011 D
b1000001111000110110011 O
b1000001111000110110011 l
bx 2
bx Y
bx Z
b1010000 .
b1010000 U
b1010000 a
b1010000 c
b1001110 -
b1001110 :
b1001110 S
b1001100 /
b1001100 ;
b1001100 N
b1001100 b
b1001100 e
bx 6
bx M
bx W
1!
#380
0!
#390
1^
1X
b1010100 (
b1010100 \
b1010100 i
b0 @
b0 B
b0 9
b0 =
b0 G
b0 H
b1 "
b1 J
1%
b0 *
b0 L
b0 R
b0 k
b0 +
b0 ?
b0 j
b1010100 1
b1010100 ]
b1010100 _
b0 8
b0 >
b0 P
b10 F
b11 C
b1 ,
b1 h
b0 &
b0 g
b0 '
b0 f
b0 4
b0 <
b0 Q
b0 `
b0 n
b0 o
b0 2
b0 Y
b0 Z
b1010100 0
b1010100 T
b1010100 d
b10000010000011 3
b10000010000011 D
b10000010000011 O
b10000010000011 l
b0 6
b0 M
b0 W
b1010100 .
b1010100 U
b1010100 a
b1010100 c
b1010000 -
b1010000 :
b1010000 S
b1010000 /
b1010000 ;
b1010000 N
b1010000 b
b1010000 e
1!
#400
0!
#410
b10000000001 2
b10000000001 Y
b10000000001 Z
b10000000001 7
b10000000001 A
b10000000001 K
b10000000001 V
b10000000001 @
b10000000001 B
b10000000001 8
b10000000001 >
b10000000001 P
b10000000001 *
b10000000001 L
b10000000001 R
b10000000001 k
b1011000 (
b1011000 \
b1011000 i
b10 ,
b10 h
b100 &
b100 g
b100 4
b100 <
b100 Q
b100 `
b100 n
b100 o
b1011000 1
b1011000 ]
b1011000 _
b1011000 0
b1011000 T
b1011000 d
b10000000010000100000011 3
b10000000010000100000011 D
b10000000010000100000011 O
b10000000010000100000011 l
b1011000 .
b1011000 U
b1011000 a
b1011000 c
b1011000 -
b1011000 :
b1011000 S
b1010100 /
b1010100 ;
b1010100 N
b1010100 b
b1010100 e
bx 6
bx M
bx W
1!
#420
0!
